Tetragrammaton/__init__.py
tetragrammaton-0.1.1.dist-info/METADATA
tetragrammaton-0.1.1.dist-info/WHEEL
tetragrammaton-0.1.1.dist-info/top_level.txt
tetragrammaton-0.1.1.dist-info/RECORD
