Metadata-Version: 2.4
Name: Tetragrammaton
Version: 0.1.1
Summary: Tetragrammaton library for Python
Author: suiGn
Classifier: Programming Language :: Python :: 3
Requires-Python: >=3.6
Dynamic: author
Dynamic: classifier
Dynamic: description
Dynamic: description-content-type
Dynamic: requires-python
Dynamic: summary
